aikit_cli/__init__.py
aikit_cli/__main__.py
aikit_cli/cli.py
aikit_cli/new.py
aikit_cli/prompts.py
aikit_cli/utils.py
aikit_cli/templates/chatbot/ollama/app/__init__.py
aikit_cli/templates/chatbot/ollama/app/config.py
aikit_cli/templates/chatbot/ollama/app/main.py
aikit_cli/templates/chatbot/ollama/app/provider.py
aikit_cli/templates/chatbot/ollama/tests/test_smoke.py
aikit_cli/templates/chatbot/openai/app/__init__.py
aikit_cli/templates/chatbot/openai/app/config.py
aikit_cli/templates/chatbot/openai/app/main.py
aikit_cli/templates/chatbot/openai/app/provider.py
aikit_cli/templates/chatbot/openai/tests/test_smoke.py
aikit_cli/templates/rag/ollama/app/__init__.py
aikit_cli/templates/rag/ollama/app/config.py
aikit_cli/templates/rag/ollama/app/embeddings.py
aikit_cli/templates/rag/ollama/app/main.py
aikit_cli/templates/rag/ollama/app/provider.py
aikit_cli/templates/rag/ollama/app/rag.py
aikit_cli/templates/rag/ollama/app/store.py
aikit_cli/templates/rag/ollama/tests/test_smoke.py
aikit_cli/templates/rag/openai/app/__init__.py
aikit_cli/templates/rag/openai/app/config.py
aikit_cli/templates/rag/openai/app/embeddings.py
aikit_cli/templates/rag/openai/app/main.py
aikit_cli/templates/rag/openai/app/rag.py
aikit_cli/templates/rag/openai/app/store.py
aikit_cli/templates/rag/openai/tests/test_smoke.py
aikit_cli-0.1.0.dist-info/licenses/LICENSE
aikit_cli-0.1.0.dist-info/METADATA
aikit_cli-0.1.0.dist-info/WHEEL
aikit_cli-0.1.0.dist-info/entry_points.txt
aikit_cli-0.1.0.dist-info/top_level.txt
aikit_cli-0.1.0.dist-info/RECORD
