Metadata-Version: 2.4
Name: aikit-cli
Version: 0.1.0
Summary: A lightweight command-line tool for scaffolding minimal AI projects.
Author-email: Ledjob <djob93@hotmail.com>
Project-URL: Homepage, https://github.com/ledjob/aikit-cli
Project-URL: Bug Tracker, https://github.com/ledjob/aikit-cli/issues
Classifier: Programming Language :: Python :: 3
Classifier: License :: OSI Approved :: MIT License
Classifier: Operating System :: OS Independent
Requires-Python: >=3.8
License-File: LICENSE
Requires-Dist: typer[all]>=0.9.0
Requires-Dist: questionary>=2.0.0
Dynamic: license-file
